tests/__init__.py
tests/run_test.py
tests/settings.py
tests/tests.py
validator/__init__.py
validator/validators.py
django_easy_validator-1.7.0.dist-info/LICENSE.txt
django_easy_validator-1.7.0.dist-info/METADATA
django_easy_validator-1.7.0.dist-info/WHEEL
django_easy_validator-1.7.0.dist-info/top_level.txt
django_easy_validator-1.7.0.dist-info/RECORD
