Metadata-Version: 2.1
Name: django-easy-validator
Version: 1.7.0
Summary: a very easy use django request POST/GET data validator
Home-page: https://github.com/youngershen/django-easy-validator
Author: Younger Shen
Author-email: shenyangang@163.com
License: MIT
Keywords: a django request POST/GET data validator
Platform: UNKNOWN
Classifier: Development Status :: 5 - Production/Stable
Classifier: Intended Audience :: Developers
Classifier: License :: OSI Approved :: MIT License
Classifier: Programming Language :: Python :: 3.6
Classifier: Programming Language :: Python :: 3.7
Classifier: Framework :: Django :: 1.6
Classifier: Framework :: Django :: 1.7
Classifier: Framework :: Django :: 1.8
Classifier: Framework :: Django :: 1.9
Classifier: Framework :: Django :: 2.0
Requires-Python: >=3.6
Requires-Dist: Django
